tess_locator/__init__.py
tess_locator/data/tess-sector-dates.csv
tess_locator/dates.py
tess_locator/locate.py
tess_locator/tesscoord.py
tess_locator-0.6.0.dist-info/LICENSE
tess_locator-0.6.0.dist-info/METADATA
tess_locator-0.6.0.dist-info/WHEEL
tess_locator-0.6.0.dist-info/RECORD
