Metadata-Version: 2.1
Name: tess-locator
Version: 0.6.0
Summary: Fast offline queries of TESS FFI positions and filenames.
Home-page: https://github.com/SSDataLab/tess-locator
License: MIT
Keywords: NASA, TESS, Astronomy
Author: Geert Barentsen
Author-email: hello@geert.io
Requires-Python: >=3.8,<4.0
Classifier: Intended Audience :: Science/Research
Classifier: License :: OSI Approved :: MIT License
Classifier: Programming Language :: Python :: 3
Classifier: Programming Language :: Python :: 3.8
Classifier: Programming Language :: Python :: 3.9
Classifier: Programming Language :: Python :: 3.10
Classifier: Programming Language :: Python :: 3.11
Classifier: Topic :: Scientific/Engineering :: Astronomy
Requires-Dist: astropy (>=5.2.0,<6.0.0)
Requires-Dist: attrs (>=23.1.0,<24.0.0)
Requires-Dist: numpy (>=1.23.0,<2.0.0)
Requires-Dist: pandas (>=1.4.4,<2.0.0)
Requires-Dist: tess-point (>=0.8,<0.9)
Requires-Dist: tqdm (>=4.51.1,<5.0.0)
Project-URL: Repository, https://github.com/SSDataLab/tess-locator
